<?xml version="1.0" encoding="utf-8"?>
<TextureAtlas imagePath="Cool Tails.png">
	<!-- Created with Adobe Animate version 21.0.7.42652 -->
	<!-- http://www.adobe.com/products/animate.html -->
	<SubTexture name="Main CT Down0000" x="10" y="10" width="428" height="478"/>
	<SubTexture name="Main CT Down0001" x="10" y="10" width="428" height="478"/>
	<SubTexture name="Main CT Down0002" x="448" y="10" width="428" height="478"/>
	<SubTexture name="Main CT Down0003" x="886" y="10" width="428" height="478"/>
	<SubTexture name="Main CT Down0004" x="1324" y="10" width="428" height="478"/>
	<SubTexture name="Main CT Down0005" x="1762" y="10" width="428" height="478"/>
	<SubTexture name="Main CT Down0006" x="1762" y="10" width="428" height="478"/>
	<SubTexture name="Main CT Down0007" x="2200" y="10" width="428" height="478"/>
	<SubTexture name="Main CT Down0008" x="2638" y="10" width="428" height="478"/>
	<SubTexture name="Main CT Down0009" x="3076" y="10" width="428" height="478"/>
	<SubTexture name="Main CT Down0010" x="3514" y="10" width="428" height="478"/>
	<SubTexture name="Main CT Down0011" x="3514" y="10" width="428" height="478"/>
	<SubTexture name="Main CT Down0012" x="3514" y="10" width="428" height="478"/>
	<SubTexture name="Main CT Down0013" x="3514" y="10" width="428" height="478"/>
	<SubTexture name="Main CT Down0014" x="3514" y="10" width="428" height="478"/>
	<SubTexture name="Main CT Down0015" x="3514" y="10" width="428" height="478"/>
	<SubTexture name="Main CT Idle0000" x="10" y="498" width="435" height="519"/>
	<SubTexture name="Main CT Idle0001" x="455" y="498" width="435" height="519"/>
	<SubTexture name="Main CT Idle0002" x="900" y="498" width="435" height="519"/>
	<SubTexture name="Main CT Idle0003" x="1345" y="498" width="435" height="519"/>
	<SubTexture name="Main CT Idle0004" x="1790" y="498" width="435" height="519"/>
	<SubTexture name="Main CT Idle0005" x="2235" y="498" width="435" height="519"/>
	<SubTexture name="Main CT Idle0006" x="2680" y="498" width="435" height="519"/>
	<SubTexture name="Main CT Idle0007" x="2680" y="498" width="435" height="519"/>
	<SubTexture name="Main CT Idle0008" x="3125" y="498" width="435" height="519"/>
	<SubTexture name="Main CT Idle0009" x="3125" y="498" width="435" height="519"/>
	<SubTexture name="Main CT Idle0010" x="3125" y="498" width="435" height="519"/>
	<SubTexture name="Main CT Idle0011" x="3125" y="498" width="435" height="519"/>
	<SubTexture name="Main CT Idle0012" x="3125" y="498" width="435" height="519"/>
	<SubTexture name="Main CT Idle0013" x="3125" y="498" width="435" height="519"/>
	<SubTexture name="Main CT Idle0014" x="3125" y="498" width="435" height="519"/>
	<SubTexture name="Main CT Left0000" x="3570" y="498" width="407" height="475"/>
	<SubTexture name="Main CT Left0001" x="3570" y="498" width="407" height="475"/>
	<SubTexture name="Main CT Left0002" x="10" y="1027" width="407" height="475"/>
	<SubTexture name="Main CT Left0003" x="10" y="1027" width="407" height="475"/>
	<SubTexture name="Main CT Left0004" x="427" y="1027" width="407" height="475"/>
	<SubTexture name="Main CT Left0005" x="844" y="1027" width="407" height="475"/>
	<SubTexture name="Main CT Left0006" x="844" y="1027" width="407" height="475"/>
	<SubTexture name="Main CT Left0007" x="1261" y="1027" width="407" height="475"/>
	<SubTexture name="Main CT Left0008" x="1261" y="1027" width="407" height="475"/>
	<SubTexture name="Main CT Left0009" x="1261" y="1027" width="407" height="475"/>
	<SubTexture name="Main CT Left0010" x="1261" y="1027" width="407" height="475"/>
	<SubTexture name="Main CT Left0011" x="1261" y="1027" width="407" height="475"/>
	<SubTexture name="Main CT Left0012" x="1261" y="1027" width="407" height="475"/>
	<SubTexture name="Main CT Left0013" x="1261" y="1027" width="407" height="475"/>
	<SubTexture name="Main CT Left0014" x="1261" y="1027" width="407" height="475"/>
	<SubTexture name="Main CT Left0015" x="1261" y="1027" width="407" height="475"/>
	<SubTexture name="Main CT Right0000" x="1678" y="1027" width="416" height="493"/>
	<SubTexture name="Main CT Right0001" x="2104" y="1027" width="416" height="493"/>
	<SubTexture name="Main CT Right0002" x="2530" y="1027" width="416" height="493"/>
	<SubTexture name="Main CT Right0003" x="2956" y="1027" width="416" height="493"/>
	<SubTexture name="Main CT Right0004" x="2956" y="1027" width="416" height="493"/>
	<SubTexture name="Main CT Right0005" x="3382" y="1027" width="416" height="493"/>
	<SubTexture name="Main CT Right0006" x="3382" y="1027" width="416" height="493"/>
	<SubTexture name="Main CT Right0007" x="10" y="1530" width="416" height="493"/>
	<SubTexture name="Main CT Right0008" x="10" y="1530" width="416" height="493"/>
	<SubTexture name="Main CT Right0009" x="10" y="1530" width="416" height="493"/>
	<SubTexture name="Main CT Right0010" x="10" y="1530" width="416" height="493"/>
	<SubTexture name="Main CT Right0011" x="10" y="1530" width="416" height="493"/>
	<SubTexture name="Main CT Right0012" x="10" y="1530" width="416" height="493"/>
	<SubTexture name="Main CT Right0013" x="10" y="1530" width="416" height="493"/>
	<SubTexture name="Main CT Right0014" x="10" y="1530" width="416" height="493"/>
	<SubTexture name="Main CT Right0015" x="10" y="1530" width="416" height="493"/>
	<SubTexture name="Main CT Right0016" x="10" y="1530" width="416" height="493"/>
	<SubTexture name="Main CT Right0017" x="10" y="1530" width="416" height="493"/>
	<SubTexture name="Main CT Right0018" x="10" y="1530" width="416" height="493"/>
	<SubTexture name="Main CT Up0000" x="436" y="1530" width="397" height="504"/>
	<SubTexture name="Main CT Up0001" x="843" y="1530" width="397" height="504"/>
	<SubTexture name="Main CT Up0002" x="1250" y="1530" width="397" height="504"/>
	<SubTexture name="Main CT Up0003" x="1657" y="1530" width="397" height="504"/>
	<SubTexture name="Main CT Up0004" x="1657" y="1530" width="397" height="504"/>
	<SubTexture name="Main CT Up0005" x="2064" y="1530" width="397" height="504"/>
	<SubTexture name="Main CT Up0006" x="2471" y="1530" width="397" height="504"/>
	<SubTexture name="Main CT Up0007" x="2878" y="1530" width="397" height="504"/>
	<SubTexture name="Main CT Up0008" x="2878" y="1530" width="397" height="504"/>
	<SubTexture name="Main CT Up0009" x="2878" y="1530" width="397" height="504"/>
	<SubTexture name="Main CT Up0010" x="3285" y="1530" width="397" height="504"/>
	<SubTexture name="Main CT Up0011" x="3285" y="1530" width="397" height="504"/>
	<SubTexture name="Main CT Up0012" x="3285" y="1530" width="397" height="504"/>
	<SubTexture name="Main CT Up0013" x="3285" y="1530" width="397" height="504"/>
	<SubTexture name="Main CT Up0014" x="3285" y="1530" width="397" height="504"/>
</TextureAtlas>
